LegendBS/__init__.py
LegendBS/abuse.py
LegendBS/banall.py
LegendBS/birthday.py
LegendBS/error.py
LegendBS/get_time.py
LegendBS/get_user.py
LegendBS/love.py
LegendBS/porn.py
LegendBS/raid.py
LegendBS/start.py
LegendBS/start_bot.py
LegendBS/start_help.py
LegendBS/startup.py
LegendBS/yup.py
pyTashriBS-0.2.dist-info/LICENSE
pyTashriBS-0.2.dist-info/METADATA
pyTashriBS-0.2.dist-info/WHEEL
pyTashriBS-0.2.dist-info/top_level.txt
pyTashriBS-0.2.dist-info/RECORD
